{
  "module": "SecretsManagementPQC",
  "use_case": "CloudSecretsComparator",
  "key_type": "CKK_AES",
  "parameter_set": "AES-256",
  "keys": [
    {
      "id": "aes256gcm-01-pub",
      "CKA_CLASS": "CKO_PUBLIC_KEY",
      "CKA_KEY_TYPE": "CKK_AES",
      "CKA_PARAMETER_SET": "AES-256",
      "value": "d09f9e6cff036789295ed3929c1294f5df7d2d07a5ab7035f635623c1aedccce"
    },
    {
      "id": "aes256gcm-01-priv",
      "CKA_CLASS": "CKO_PRIVATE_KEY",
      "CKA_KEY_TYPE": "CKK_AES",
      "CKA_PARAMETER_SET": "AES-256",
      "value": "5f300c3b45cee1ade3a0978770ace506291b3464a01b962665a5c105208c493e"
    }
  ]
}
